{"1":{
    "id": 1,
    "id_mascota": "M-0001",
    "nombre": "Mía Herrera",
    "raza": "Husky",
    "descripcion": "Husky color gris con blanco y manchas negras",
    "en_adopcion": false,
    "esta_perdida": false,
    "propietario": 2
    },
"2":{
    "id": 2,
    "id_mascota": "M-0002",
    "nombre": "Pily",
    "raza": "Labrador",
    "descripcion": "Perrita de 3 meses de nacida",
    "en_adopcion": true,
    "esta_perdida": false,
    "propietario": 1
    },
    "3":{
    "id": 3,
    "id_mascota": "M-0010",
    "nombre": "Perla",
    "raza": "Castellana",
    "descripcion": "Es de color blanco calido",
    "en_adopcion": false,
    "esta_perdida": false,
    "propietario": 2
    },
    "4":{
    "id": 4,
    "id_mascota": "M-0025",
    "nombre": "Tino",
    "raza": "Snowser",
    "descripcion": "Color gris combiando con machas amarrillas",
    "esta_perdida": false,
    "en_adopcion" : true,
    "propietario": 3
    }
}